mt/cv/__init__.py
mt/opencv/__init__.py
mt/opencv/ansi.py
mt/opencv/image.py
mt/opencv/imgcrop.py
mt/opencv/imgres.py
mt/opencv/polygon.py
mt/opencv/version.py
mt/opencv/warping.py
mtopencv-1.11.15.data/scripts/draw_chessboard_corners
mtopencv-1.11.15.dist-info/licenses/LICENSE
mtopencv-1.11.15.dist-info/METADATA
mtopencv-1.11.15.dist-info/WHEEL
mtopencv-1.11.15.dist-info/top_level.txt
mtopencv-1.11.15.dist-info/RECORD
