Metadata-Version: 2.4
Name: mtopencv
Version: 1.11.15
Summary: Minh-Tri Pham's extra modules using OpenCV
Author: Minh-Tri Pham
License-File: LICENSE
Requires-Dist: ansicolors
Requires-Dist: shapely
Requires-Dist: pyturbojpeg
Requires-Dist: mtbase>=4.33.6
Requires-Dist: mtgeo>=1.1.14
Dynamic: author
Dynamic: license-file
Dynamic: requires-dist
Dynamic: summary
